pytest_arraydiff/__init__.py
pytest_arraydiff/plugin.py
pytest_arraydiff/version.py
pytest_arraydiff-0.6.1.dist-info/LICENSE
pytest_arraydiff-0.6.1.dist-info/METADATA
pytest_arraydiff-0.6.1.dist-info/WHEEL
pytest_arraydiff-0.6.1.dist-info/entry_points.txt
pytest_arraydiff-0.6.1.dist-info/top_level.txt
pytest_arraydiff-0.6.1.dist-info/RECORD
