Metadata-Version: 2.1
Name: pytest-arraydiff
Version: 0.6.1
Summary: pytest plugin to help with comparing array output from tests
Home-page: https://github.com/astropy/pytest-arraydiff
Author: The Astropy Developers
Author-email: astropy.team@gmail.com
License: BSD
Classifier: Development Status :: 4 - Beta
Classifier: Framework :: Pytest
Classifier: Intended Audience :: Developers
Classifier: License :: OSI Approved :: BSD License
Classifier: Operating System :: OS Independent
Classifier: Programming Language :: Python
Classifier: Programming Language :: Python :: 3
Classifier: Programming Language :: Python :: 3 :: Only
Classifier: Programming Language :: Python :: 3.7
Classifier: Programming Language :: Python :: 3.8
Classifier: Programming Language :: Python :: 3.9
Classifier: Programming Language :: Python :: 3.10
Classifier: Programming Language :: Python :: 3.11
Classifier: Programming Language :: Python :: 3.12
Classifier: Programming Language :: Python :: Implementation :: CPython
Classifier: Topic :: Software Development :: Testing
Classifier: Topic :: Utilities
Requires-Python: >=3.7
License-File: LICENSE
Requires-Dist: pytest>=4.6
Requires-Dist: numpy
Provides-Extra: test
Requires-Dist: astropy; extra == "test"
Requires-Dist: pandas; extra == "test"
Requires-Dist: tables; extra == "test"
